omnimind/__init__.py
omnimind/cli.py
omnimind/engine.py
omnimind/server.py
omnimind/unified.py
omnimind/workflow.py
omnimind/cognitive/__init__.py
omnimind/cognitive/anti_repetition.py
omnimind/cognitive/realtime.py
omnimind/cognitive/standard_tools.py
omnimind/cognitive/thinking_engine.py
omnimind/cognitive/tool_use.py
omnimind/cognitive/uncertainty_detector.py
omnimind/conversion/__init__.py
omnimind/conversion/advanced_conversion.py
omnimind/conversion/gguf_export.py
omnimind/conversion/low_memory.py
omnimind/conversion/weight_transfer.py
omnimind/core/__init__.py
omnimind/core/state_processor.py
omnimind/data/__init__.py
omnimind/data/dataprep.py
omnimind/data/documents.py
omnimind/data/synthetic.py
omnimind/generation/__init__.py
omnimind/generation/document_generator.py
omnimind/generation/media_generator.py
omnimind/inference/__init__.py
omnimind/inference/disk_streaming.py
omnimind/inference/gpu_optimization.py
omnimind/inference/hyper_inference.py
omnimind/inference/mobile.py
omnimind/inference/ultra_fast.py
omnimind/interface/__init__.py
omnimind/interface/text_interface.py
omnimind/interface/voice_interface.py
omnimind/kernels/__init__.py
omnimind/kernels/cross_entropy.py
omnimind/kernels/geglu.py
omnimind/kernels/layernorm.py
omnimind/kernels/moe.py
omnimind/kernels/quant_matmul.py
omnimind/kernels/rope.py
omnimind/kernels/ssm.py
omnimind/kernels/swiglu.py
omnimind/memory/__init__.py
omnimind/memory/episodic_memory.py
omnimind/memory/memory_manager.py
omnimind/memory/semantic_memory.py
omnimind/memory/working_memory.py
omnimind/model/__init__.py
omnimind/model/config.py
omnimind/model/fast_base.py
omnimind/model/fast_gemma.py
omnimind/model/fast_llama.py
omnimind/model/lite.py
omnimind/model/moe_ssm.py
omnimind/model/multimodal.py
omnimind/model/music.py
omnimind/model/omnimind_model.py
omnimind/model/sparse_experts.py
omnimind/model/ssm_layer.py
omnimind/model/turbo_streaming.py
omnimind/quantization/__init__.py
omnimind_ai-0.2.10.dist-info/METADATA
omnimind_ai-0.2.10.dist-info/WHEEL
omnimind_ai-0.2.10.dist-info/entry_points.txt
omnimind_ai-0.2.10.dist-info/top_level.txt
omnimind_ai-0.2.10.dist-info/RECORD
