Metadata-Version: 2.4
Name: omnimind-ai
Version: 0.2.10
Summary: State-Space Language Model - Scalable AI for any device with unlimited memory
Home-page: https://github.com/kue-kid/omnimind
Author: OMNIMIND Team
Project-URL: Homepage, https://github.com/kue-kid/omnimind
Project-URL: Repository, https://github.com/kue-kid/omnimind
Keywords: ai,llm,state-space,mamba,language-model,thai,ssm
Classifier: Development Status :: 4 - Beta
Classifier: Intended Audience :: Developers
Classifier: Intended Audience :: Science/Research
Classifier: Programming Language :: Python :: 3
Classifier: Programming Language :: Python :: 3.10
Classifier: Programming Language :: Python :: 3.11
Classifier: Programming Language :: Python :: 3.12
Classifier: Topic :: Scientific/Engineering :: Artificial Intelligence
Requires-Python: >=3.8
Requires-Dist: torch>=2.0.0
Requires-Dist: einops>=0.8.0
Requires-Dist: tqdm>=4.67.0
Requires-Dist: safetensors
Requires-Dist: jinja2
Requires-Dist: fire
Requires-Dist: fastapi
Requires-Dist: uvicorn
Requires-Dist: orjson
Requires-Dist: uvloop
Provides-Extra: train
Requires-Dist: accelerate>=1.12.0; extra == "train"
Requires-Dist: sentencepiece>=0.2.0; extra == "train"
Requires-Dist: tokenizers>=0.22.0; extra == "train"
Requires-Dist: transformers>=4.57.0; extra == "train"
Requires-Dist: datasets>=3.3.0; extra == "train"
Requires-Dist: peft>=0.14.0; extra == "train"
Requires-Dist: bitsandbytes>=0.45.0; extra == "train"
Provides-Extra: memory
Requires-Dist: chromadb>=0.6.0; extra == "memory"
Requires-Dist: sentence-transformers>=3.4.0; extra == "memory"
Provides-Extra: server
Requires-Dist: fastapi>=0.115.0; extra == "server"
Requires-Dist: uvicorn>=0.34.0; extra == "server"
Provides-Extra: all
Requires-Dist: accelerate>=1.12.0; extra == "all"
Requires-Dist: sentencepiece>=0.2.0; extra == "all"
Requires-Dist: tokenizers>=0.22.0; extra == "all"
Requires-Dist: transformers>=4.57.0; extra == "all"
Requires-Dist: datasets>=3.3.0; extra == "all"
Requires-Dist: peft>=0.14.0; extra == "all"
Requires-Dist: bitsandbytes>=0.45.0; extra == "all"
Requires-Dist: chromadb>=0.6.0; extra == "all"
Requires-Dist: sentence-transformers>=3.4.0; extra == "all"
Requires-Dist: fastapi>=0.115.0; extra == "all"
Requires-Dist: uvicorn>=0.34.0; extra == "all"
Requires-Dist: safetensors>=0.5.0; extra == "all"
Requires-Dist: huggingface_hub>=0.28.0; extra == "all"
Requires-Dist: jinja2>=3.1.0; extra == "all"
Requires-Dist: openai-whisper; extra == "all"
Requires-Dist: edge-tts; extra == "all"
Requires-Dist: Pillow; extra == "all"
Requires-Dist: torchvision; extra == "all"
Requires-Dist: opencv-python; extra == "all"
Requires-Dist: torchaudio; extra == "all"
Requires-Dist: librosa; extra == "all"
Requires-Dist: diffusers; extra == "all"
Requires-Dist: scipy; extra == "all"
Requires-Dist: numpy; extra == "all"
Requires-Dist: matplotlib; extra == "all"
Requires-Dist: sympy; extra == "all"
Requires-Dist: requests; extra == "all"
Requires-Dist: beautifulsoup4; extra == "all"
Provides-Extra: voice
Requires-Dist: openai-whisper; extra == "voice"
Requires-Dist: edge-tts; extra == "voice"
Provides-Extra: vision
Requires-Dist: Pillow; extra == "vision"
Requires-Dist: torchvision; extra == "vision"
Requires-Dist: opencv-python; extra == "vision"
Provides-Extra: audio
Requires-Dist: torchaudio; extra == "audio"
Requires-Dist: librosa; extra == "audio"
Provides-Extra: generation
Requires-Dist: diffusers; extra == "generation"
Requires-Dist: transformers; extra == "generation"
Requires-Dist: scipy; extra == "generation"
Provides-Extra: science
Requires-Dist: numpy; extra == "science"
Requires-Dist: matplotlib; extra == "science"
Requires-Dist: sympy; extra == "science"
Requires-Dist: requests; extra == "science"
Requires-Dist: beautifulsoup4; extra == "science"
Dynamic: home-page
Dynamic: requires-python
